mops/__init__.py
mops/exceptions.py
mops/js_scripts.py
mops/keyboard_keys.py
mops/shared_utils.py
mops/visual_comparison.py
mops/abstraction/driver_wrapper_abc.py
mops/abstraction/element_abc.py
mops/abstraction/mixin_abc.py
mops/abstraction/page_abc.py
mops/base/driver_wrapper.py
mops/base/element.py
mops/base/group.py
mops/base/page.py
mops/mixins/driver_mixin.py
mops/mixins/internal_mixin.py
mops/mixins/native_context.py
mops/mixins/objects/box.py
mops/mixins/objects/cut_box.py
mops/mixins/objects/driver.py
mops/mixins/objects/location.py
mops/mixins/objects/locator.py
mops/mixins/objects/scrolls.py
mops/mixins/objects/size.py
mops/mixins/objects/wait_result.py
mops/playwright/play_driver.py
mops/playwright/play_element.py
mops/playwright/play_page.py
mops/selenium/sel_utils.py
mops/selenium/core/core_driver.py
mops/selenium/core/core_element.py
mops/selenium/core/core_page.py
mops/selenium/driver/mobile_driver.py
mops/selenium/driver/web_driver.py
mops/selenium/elements/mobile_element.py
mops/selenium/elements/web_element.py
mops/selenium/pages/mobile_page.py
mops/selenium/pages/web_page.py
mops/utils/internal_utils.py
mops/utils/logs.py
mops/utils/previous_object_driver.py
mops/utils/selector_synchronizer.py
dyatel_wrapper-3.0.0a1.dist-info/METADATA
dyatel_wrapper-3.0.0a1.dist-info/WHEEL
dyatel_wrapper-3.0.0a1.dist-info/top_level.txt
dyatel_wrapper-3.0.0a1.dist-info/RECORD
