Metadata-Version: 2.1
Name: dyatel-wrapper
Version: 3.0.0a1
Summary: Wrapper of Selenium, Appium and Playwright with single API
Author-email: Podolian Vladimir <vladimir.podolyan64@gmail.com>
License: MIT
Project-URL: Changelog, https://github.com/CustomEnv/dyatel/blob/master/CHANGELOG.md
Project-URL: Documentation, https://dyatel.readthedocs.io
Project-URL: Homepage, https://github.com/CustomEnv/dyatel
Project-URL: Source, https://github.com/CustomEnv/dyatel
Project-URL: Tracker, https://github.com/CustomEnv/dyatel/issues
Classifier: Development Status :: 4 - Beta
Classifier: License :: OSI Approved :: MIT License
Classifier: Programming Language :: Python :: 3.8
Classifier: Programming Language :: Python :: 3.9
Classifier: Programming Language :: Python :: 3.10
Classifier: Programming Language :: Python :: 3.11
Classifier: Programming Language :: Python :: 3.12
Classifier: Topic :: Software Development :: Libraries :: Python Modules
Classifier: Topic :: Software Development :: Quality Assurance
Classifier: Topic :: Software Development :: Testing :: Acceptance
Requires-Python: >=3.8
Requires-Dist: Appium-Python-Client >=3.1.0
Requires-Dist: playwright >=1.41.0
Requires-Dist: selenium >=4.12.0
Requires-Dist: numpy >=2.0.1 ; python_version >= "3.11"
Requires-Dist: opencv-python >=4.10.0.84 ; python_version >= "3.11"
Requires-Dist: scikit-image >=0.24.0 ; python_version >= "3.11"
Requires-Dist: Pillow >=10.4.0 ; python_version >= "3.12"
Requires-Dist: numpy <2.0.0,>=1.24.2 ; python_version >= "3.8" and python_version <= "3.10"
Requires-Dist: opencv-python <4.10.0.84,>=4.5.5.64 ; python_version >= "3.8" and python_version <= "3.10"
Requires-Dist: scikit-image <0.24.0,>=0.20.0 ; python_version >= "3.8" and python_version <= "3.10"
Requires-Dist: Pillow <10.4.0,>=9.4.0 ; python_version >= "3.8" and python_version <= "3.11"
